python_algorithm_examples/__init__.py
python_algorithm_examples/fibonacci.py
python_algorithm_examples-0.1.2.dist-info/METADATA
python_algorithm_examples-0.1.2.dist-info/WHEEL
python_algorithm_examples-0.1.2.dist-info/licenses/LICENSE
python_algorithm_examples-0.1.2.dist-info/RECORD
