Metadata-Version: 2.1
Name: python-algorithm-examples
Version: 0.1.2
Summary: Examples of algorithms in Python
Project-URL: GitHub Repository, https://github.com/cicirello/python-algorithm-examples
Project-URL: Bug Tracker, https://github.com/cicirello/python-algorithm-examples/issues
Project-URL: Changelog, https://github.com/cicirello/python-algorithm-examples/blob/main/CHANGELOG.md
Author-email: "Vincent A. Cicirello" <development@cicirello.org>
License-File: LICENSE
Keywords: algorithms,data structures
Classifier: Intended Audience :: Education
Classifier: Intended Audience :: Science/Research
Classifier: License :: OSI Approved :: GNU General Public License v3 (GPLv3)
Classifier: Operating System :: OS Independent
Classifier: Programming Language :: Python :: 3
Classifier: Topic :: Education
Classifier: Topic :: Other/Nonlisted Topic
Classifier: Topic :: Scientific/Engineering
Requires-Python: >=3.11
